CHANGES.txt
README.txt
TODO.txt
bootstrap.py
buildout.cfg
setup.cfg
setup.py
test-plone-3.x.cfg
test-plone-4.x.cfg
collective/__init__.py
collective.salesforce.rsvp.egg-info/PKG-INFO
collective.salesforce.rsvp.egg-info/SOURCES.txt
collective.salesforce.rsvp.egg-info/dependency_links.txt
collective.salesforce.rsvp.egg-info/entry_points.txt
collective.salesforce.rsvp.egg-info/namespace_packages.txt
collective.salesforce.rsvp.egg-info/not-zip-safe
collective.salesforce.rsvp.egg-info/requires.txt
collective.salesforce.rsvp.egg-info/top_level.txt
collective/salesforce/__init__.py
collective/salesforce/rsvp/__init__.py
collective/salesforce/rsvp/config.py
collective/salesforce/rsvp/configure.zcml
collective/salesforce/rsvp/events.zcml
collective/salesforce/rsvp/fields.py
collective/salesforce/rsvp/helpers.py
collective/salesforce/rsvp/interfaces.py
collective/salesforce/rsvp/profiles.zcml
collective/salesforce/rsvp/rsvpable.py
collective/salesforce/rsvp/validators.py
collective/salesforce/rsvp/version.txt
collective/salesforce/rsvp/browser/__init__.py
collective/salesforce/rsvp/browser/configuration.py
collective/salesforce/rsvp/browser/configure.zcml
collective/salesforce/rsvp/browser/forms.py
collective/salesforce/rsvp/browser/registration.py
collective/salesforce/rsvp/browser/rsvp.kss
collective/salesforce/rsvp/browser/templates/registration-form.pt
collective/salesforce/rsvp/browser/templates/registration-viewlet.pt
collective/salesforce/rsvp/profiles/default/actionicons.xml
collective/salesforce/rsvp/profiles/default/actions.xml
collective/salesforce/rsvp/profiles/default/componentregistry.xml
collective/salesforce/rsvp/profiles/default/kssregistry.xml
collective/salesforce/rsvp/profiles/default/viewlets.xml
collective/salesforce/rsvp/tests/__init__.py
collective/salesforce/rsvp/tests/base.py
collective/salesforce/rsvp/tests/test_interfaces.py
collective/salesforce/rsvp/tests/test_registration.py
collective/salesforce/rsvp/tests/test_rsvp_configuration.py
collective/salesforce/rsvp/tests/test_schema.py
collective/salesforce/rsvp/tests/test_setup.py
collective/salesforce/rsvp/tests/test_uninstall.py
docs/CONFIGURATION-TIPS.txt
docs/CREDITS.txt
docs/INSTALL.txt
docs/LICENSE.GPL
docs/LICENSE.txt
docs/RUNNING-TESTS.txt