Metadata-Version: 1.0
Name: collective.salesforce.rsvp
Version: 1.3
Summary: RSVP/Event registration system integrating the Plone content management system with       the Salesforce.com customer relationship management system.
Home-page: http://groups.google.com/group/plonesf
Author: David Glick, Groundwire
Author-email: davidglick@groundwire.org
License: GPL
Keywords: Zope CMF Plone Salesforce.com CRM registration
Platform: UNKNOWN
Classifier: Framework :: Plone
Classifier: Framework :: Zope2
Classifier: Programming Language :: Python
Classifier: Topic :: Software Development :: Libraries :: Python Modules
Classifier: Development Status :: 5 - Production/Stable
